{
  "@type" : "sc:AnnotationList",
  "resources" : [ {
    "resource" : [ {
      "http://dev.llgc.org.uk/sas/full_text" : "Details and decorations",
      "@type" : "dctypes:Text",
      "format" : "text/html",
      "chars" : "<p>Details and decorations</p>"
    } ],
    "@type" : "oa:Annotation",
    "dcterms:creator" : "https://dev.gdmrdigital.com/user/1245635613/151624434",
    "motivation" : [ "oa:commenting" ],
    "dcterms:created" : "2023-12-14T14:58:20",
    "@id" : "https://dev.gdmrdigital.com/annotation/anno/1702565900230",
    "dcterms:modified" : "2023-12-14T15:35:19",
    "@context" : "file:/usr/local/tomcat/webapps/ROOT/contexts/iiif-2.0.json",
    "on" : [ {
      "within" : {
        "@type" : "sc:Manifest",
        "@id" : "https://MaddalenaA.github.io/project_ships/manifests/manifest_ships2.json"
      },
      "@type" : "oa:SpecificResource",
      "selector" : {
        "default" : {
          "@type" : "oa:FragmentSelector",
          "value" : "xywh=1658,2554,1338,1840"
        },
        "item" : {
          "@type" : "oa:SvgSelector",
          "value" : "<svg xmlns='http://www.w3.org/2000/svg'><path xmlns=\"http://www.w3.org/2000/svg\" d=\"M1658.3913,2554.16087h668.75362v0h668.75362v919.82899v919.82899h-668.75362h-668.75362v-919.82899z\" data-paper-data=\"{&quot;strokeWidth&quot;:1,&quot;rotation&quot;:0,&quot;annotation&quot;:null,&quot;nonHoverStrokeColor&quot;:[&quot;Color&quot;,0,0.74902,1],&quot;editable&quot;:true,&quot;deleteIcon&quot;:null,&quot;rotationIcon&quot;:null,&quot;group&quot;:null}\" id=\"rectangle_4abf4218-8289-40bd-8713-1de7516cae00\" fill-opacity=\"0.00001\" fill=\"#00bfff\" fill-rule=\"nonzero\" stroke=\"#00bfff\" stroke-width=\"1\" stroke-linecap=\"butt\" stroke-linejoin=\"miter\" stroke-miterlimit=\"10\" stroke-dasharray=\"\" stroke-dashoffset=\"0\" font-family=\"none\" font-weight=\"none\" font-size=\"none\" text-anchor=\"none\" style=\"mix-blend-mode: normal\"/></svg>"
        },
        "@type" : "oa:Choice"
      },
      "full" : "https://gallica.bnf.fr/iiif/ark:/12148/bpt6k5699565s/canvas/f42"
    } ]
  }, {
    "resource" : [ {
      "http://dev.llgc.org.uk/sas/full_text" : "<p style=\"margin-bottom: 0cm; border: 1px solid #d9d9e3; padding: 0.05cm;\">Section of the aft&nbsp;",
      "@type" : "dctypes:Text",
      "format" : "text/html",
      "chars" : "<p style=\"margin-bottom: 0cm; border: 1px solid #d9d9e3; padding: 0.05cm;\">Section of the aft&nbsp;</p>"
    } ],
    "@type" : "oa:Annotation",
    "dcterms:creator" : "https://dev.gdmrdigital.com/user/1245635613/151624434",
    "motivation" : [ "oa:commenting" ],
    "dcterms:created" : "2023-12-14T14:56:24",
    "@id" : "https://dev.gdmrdigital.com/annotation/anno/1702565784468",
    "dcterms:modified" : "2023-12-14T15:35:28",
    "@context" : "file:/usr/local/tomcat/webapps/ROOT/contexts/iiif-2.0.json",
    "on" : [ {
      "within" : {
        "@type" : "sc:Manifest",
        "@id" : "https://MaddalenaA.github.io/project_ships/manifests/manifest_ships2.json"
      },
      "@type" : "oa:SpecificResource",
      "selector" : {
        "default" : {
          "@type" : "oa:FragmentSelector",
          "value" : "xywh=1112,444,1141,1916"
        },
        "item" : {
          "@type" : "oa:SvgSelector",
          "value" : "<svg xmlns='http://www.w3.org/2000/svg'><path xmlns=\"http://www.w3.org/2000/svg\" d=\"M2252.88696,2360.17391h-570.64609v0h-570.64609v-958.04261v-958.04261h570.64609h570.64609v958.04261z\" data-paper-data=\"{&quot;strokeWidth&quot;:1,&quot;rotation&quot;:0,&quot;annotation&quot;:null,&quot;nonHoverStrokeColor&quot;:[&quot;Color&quot;,0,0.74902,1],&quot;editable&quot;:true,&quot;deleteIcon&quot;:null,&quot;rotationIcon&quot;:null,&quot;group&quot;:null}\" id=\"rectangle_a88d028e-6d1f-4cc5-bd41-e4b142810297\" fill-opacity=\"0.00001\" fill=\"#00bfff\" fill-rule=\"nonzero\" stroke=\"#00bfff\" stroke-width=\"1\" stroke-linecap=\"butt\" stroke-linejoin=\"miter\" stroke-miterlimit=\"10\" stroke-dasharray=\"\" stroke-dashoffset=\"0\" font-family=\"none\" font-weight=\"none\" font-size=\"none\" text-anchor=\"none\" style=\"mix-blend-mode: normal\"/></svg>"
        },
        "@type" : "oa:Choice"
      },
      "full" : "https://gallica.bnf.fr/iiif/ark:/12148/bpt6k5699565s/canvas/f42"
    } ]
  }, {
    "resource" : [ {
      "http://dev.llgc.org.uk/sas/full_text" : "<p style=\"margin-bottom: 0cm; border: 1px solid #d9d9e3; padding: 0.05cm;\">Demonstration of the bowsprit platform of the Royal Louis in 1726",
      "@type" : "dctypes:Text",
      "format" : "text/html",
      "chars" : "<p style=\"margin-bottom: 0cm; border: 1px solid #d9d9e3; padding: 0.05cm;\">Demonstration of the bowsprit platform of the Royal Louis in 1726</p>"
    } ],
    "@type" : "oa:Annotation",
    "dcterms:creator" : "https://dev.gdmrdigital.com/user/1245635613/151624434",
    "motivation" : [ "oa:commenting" ],
    "dcterms:created" : "2023-12-14T14:57:57",
    "@id" : "https://dev.gdmrdigital.com/annotation/anno/1702565877678",
    "dcterms:modified" : "2023-12-14T15:37:16",
    "@context" : "file:/usr/local/tomcat/webapps/ROOT/contexts/iiif-2.0.json",
    "on" : [ {
      "within" : {
        "@type" : "sc:Manifest",
        "@id" : "https://MaddalenaA.github.io/project_ships/manifests/manifest_ships2.json"
      },
      "@type" : "oa:SpecificResource",
      "selector" : {
        "default" : {
          "@type" : "oa:FragmentSelector",
          "value" : "xywh=4735,2383,1391,1145"
        },
        "item" : {
          "@type" : "oa:SvgSelector",
          "value" : "<svg xmlns='http://www.w3.org/2000/svg'><path xmlns=\"http://www.w3.org/2000/svg\" d=\"M4735.4,2383.21594h695.46377v0h695.46377v572.5971v572.5971h-695.46377h-695.46377v-572.5971z\" data-paper-data=\"{&quot;strokeWidth&quot;:1,&quot;rotation&quot;:0,&quot;annotation&quot;:null,&quot;nonHoverStrokeColor&quot;:[&quot;Color&quot;,0,0.74902,1],&quot;editable&quot;:true}\" id=\"rectangle_33c9e480-95b5-4c09-8593-03602dbf3da2\" fill-opacity=\"0.00001\" fill=\"#00bfff\" fill-rule=\"nonzero\" stroke=\"#00bfff\" stroke-width=\"56.49567\" stroke-linecap=\"butt\" stroke-linejoin=\"miter\" stroke-miterlimit=\"10\" stroke-dasharray=\"\" stroke-dashoffset=\"0\" font-family=\"none\" font-weight=\"none\" font-size=\"none\" text-anchor=\"none\" style=\"mix-blend-mode: normal\"/></svg>"
        },
        "@type" : "oa:Choice"
      },
      "full" : "https://gallica.bnf.fr/iiif/ark:/12148/bpt6k5699565s/canvas/f42"
    } ]
  }, {
    "resource" : [ {
      "http://dev.llgc.org.uk/sas/full_text" : "<p style=\"border: 1px solid #d9d9e3; padding: 0.05cm;\">Plan of the main chambers at the aft&nbsp;",
      "@type" : "dctypes:Text",
      "format" : "text/html",
      "chars" : "<p style=\"border: 1px solid #d9d9e3; padding: 0.05cm;\">Plan of the main chambers at the aft&nbsp;</p>"
    } ],
    "@type" : "oa:Annotation",
    "dcterms:creator" : "https://dev.gdmrdigital.com/user/1245635613/151624434",
    "motivation" : [ "oa:commenting" ],
    "dcterms:created" : "2023-12-14T14:57:14",
    "@id" : "https://dev.gdmrdigital.com/annotation/anno/1702565834541",
    "dcterms:modified" : "2023-12-14T15:35:10",
    "@context" : "file:/usr/local/tomcat/webapps/ROOT/contexts/iiif-2.0.json",
    "on" : [ {
      "within" : {
        "@type" : "sc:Manifest",
        "@id" : "https://MaddalenaA.github.io/project_ships/manifests/manifest_ships2.json"
      },
      "@type" : "oa:SpecificResource",
      "selector" : {
        "default" : {
          "@type" : "oa:FragmentSelector",
          "value" : "xywh=366,2511,1231,2120"
        },
        "item" : {
          "@type" : "oa:SvgSelector",
          "value" : "<svg xmlns='http://www.w3.org/2000/svg'><path xmlns=\"http://www.w3.org/2000/svg\" d=\"M365.62029,2511.42464h615.33333v0h615.33333v1060.13551v1060.13551h-615.33333h-615.33333v-1060.13551z\" data-paper-data=\"{&quot;strokeWidth&quot;:1,&quot;rotation&quot;:0,&quot;annotation&quot;:null,&quot;nonHoverStrokeColor&quot;:[&quot;Color&quot;,0,0.74902,1],&quot;editable&quot;:true,&quot;deleteIcon&quot;:null,&quot;rotationIcon&quot;:null,&quot;group&quot;:null}\" id=\"rectangle_e9bab537-1ba9-470d-84c4-8074545b3332\" fill-opacity=\"0.00001\" fill=\"#00bfff\" fill-rule=\"nonzero\" stroke=\"#00bfff\" stroke-width=\"1\" stroke-linecap=\"butt\" stroke-linejoin=\"miter\" stroke-miterlimit=\"10\" stroke-dasharray=\"\" stroke-dashoffset=\"0\" font-family=\"none\" font-weight=\"none\" font-size=\"none\" text-anchor=\"none\" style=\"mix-blend-mode: normal\"/></svg>"
        },
        "@type" : "oa:Choice"
      },
      "full" : "https://gallica.bnf.fr/iiif/ark:/12148/bpt6k5699565s/canvas/f42"
    } ]
  } ],
  "@id" : "https://MaddalenaA.github.io/project_ships/annotations/1ba17396ce06eb00990c9bf2b89281e5.json",
  "@context" : "http://iiif.io/api/presentation/2/context.json"
}